labelme_to_yolo/__init__.py
labelme_to_yolo/__main__.py
labelme_to_yolo/datatypes.py
labelme_to_yolo-0.2.0.dist-info/METADATA
labelme_to_yolo-0.2.0.dist-info/WHEEL
labelme_to_yolo-0.2.0.dist-info/entry_points.txt
labelme_to_yolo-0.2.0.dist-info/RECORD
