Metadata-Version: 2.1
Name: labelme-to-yolo
Version: 0.2.0
Summary: A tool to convert LabelMe dataset annotations into YOLO format for instance segmentation.
Home-page: https://github.com/Tlaloc-Es/labelme-to-yolo
License: MIT
Author: Tlaloc-Es
Author-email: dev@tlaloc-es.com
Requires-Python: >=3.10,<4.0
Classifier: License :: OSI Approved :: MIT License
Classifier: Programming Language :: Python :: 3
Classifier: Programming Language :: Python :: 3.10
Classifier: Programming Language :: Python :: 3.11
Classifier: Programming Language :: Python :: 3.12
Classifier: Programming Language :: Python :: 3.13
Requires-Dist: albumentations (>=1.3.0,<2.0.0)
Requires-Dist: click
Requires-Dist: numpy
Requires-Dist: pydantic
Requires-Dist: pyyaml
Project-URL: Repository, https://github.com/Tlaloc-Es/labelme-to-yolo
